convertecritures-1.2.0.dist-info/licenses/LICENSE.txt
py_convert/__about__.py
py_convert/__init__.py
py_convert/cli.py
py_convert/error.py
py_convert/settings_manager.py
convertecritures-1.2.0.dist-info/METADATA
convertecritures-1.2.0.dist-info/WHEEL
convertecritures-1.2.0.dist-info/entry_points.txt
convertecritures-1.2.0.dist-info/top_level.txt
convertecritures-1.2.0.dist-info/RECORD
