Metadata-Version: 2.4
Name: ConvertEcritures
Version: 1.2.0
Summary: Convertisseur d'écritures comptables d'un format à un autre format.
Author: Michaël AUGUSTE
License-Expression: MIT
Project-URL: Homepage, https://github.com/Atem83/ConvertEcritures
Project-URL: Changelog, https://github.com/Atem83/ConvertEcritures/blob/main/CHANGELOG.md
Project-URL: DOWNLOAD, https://github.com/Atem83/ConvertEcritures/releases
Classifier: Operating System :: OS Independent
Classifier: Programming Language :: Python
License-File: LICENSE.txt
Requires-Dist: polars
Requires-Dist: PySide6
Requires-Dist: dateparser
Requires-Dist: openpyxl
Requires-Dist: xlsxwriter
Requires-Dist: fastexcel
Requires-Dist: screeninfo
Requires-Dist: send2trash
Dynamic: license-file
